oyster_twitter_sdk/__init__.py
twitter_sdk/__init__.py
oyster_twitter_sdk-0.0.2.dist-info/LICENSE
oyster_twitter_sdk-0.0.2.dist-info/METADATA
oyster_twitter_sdk-0.0.2.dist-info/WHEEL
oyster_twitter_sdk-0.0.2.dist-info/top_level.txt
oyster_twitter_sdk-0.0.2.dist-info/RECORD
